{
    "configuration": {
        "module": [
            null,
            null,
            null,
            null,
            {
                "ccr": "0",
                "chips": [
                    {
                        "address": 0,
                        "reg_01": 67319277,
                        "reg_02": 25676383,
                        "reg_03": 158515308,
                        "reg_10": 0,
                        "reg_11": 0,
                        "reg_12": 0,
                        "reg_13": 0,
                        "reg_14": 0,
                        "reg_15": 0,
                        "reg_16": 0,
                        "reg_17": 0,
                        "reg_20": 137363512,
                        "reg_21": 1124073984,
                        "reg_40": 601232381,
                        "reg_41": 3996974590,
                        "reg_42": 253963183,
                        "reg_43": 1455304688,
                        "reg_44": 3000180962,
                        "reg_45": 1105866495,
                        "reg_46": 4242616567,
                        "reg_47": 4213362585,
                        "reg_48": 888467264,
                        "reg_49": 3824276708,
                        "reg_4a": 3039760852,
                        "reg_4b": 3840011496,
                        "reg_4c": 3221150229,
                        "reg_4d": 434889505,
                        "reg_4e": 515891200,
                        "reg_4f": 4142643198,
                        "reg_50": 3485658573,
                        "reg_51": 284167245,
                        "reg_52": 3507728863,
                        "reg_53": 4091367408,
                        "reg_54": 276818621,
                        "reg_55": 4076086864,
                        "reg_56": 365322732,
                        "reg_57": 4036083976,
                        "reg_58": 1440549599,
                        "reg_59": 2697707779,
                        "reg_5a": 2670866641,
                        "reg_5b": 2959400256,
                        "reg_5c": 3755092214,
                        "reg_5d": 3850543375,
                        "reg_5e": 4024240130,
                        "reg_5f": 1982564062,
                        "reg_60": 3384287452,
                        "reg_61": 823969885,
                        "reg_62": 1349342675,
                        "reg_63": 1149748995,
                        "reg_64": 1232394768,
                        "reg_65": 1474060256,
                        "reg_66": 1933395912,
                        "reg_67": 3893327389,
                        "reg_68": 4294967295,
                        "reg_69": 4294967295,
                        "reg_6a": 4294967295,
                        "reg_6b": 4294967295,
                        "reg_6c": 4294967295,
                        "reg_6d": 4294967295,
                        "reg_6e": 4294967295,
                        "reg_6f": 4294967295
                    },
                    {
                        "address": 1,
                        "reg_01": 67319277,
                        "reg_02": 25676383,
                        "reg_03": 158531692,
                        "reg_10": 0,
                        "reg_11": 0,
                        "reg_12": 0,
                        "reg_13": 0,
                        "reg_14": 0,
                        "reg_15": 0,
                        "reg_16": 0,
                        "reg_17": 0,
                        "reg_20": 137363512,
                        "reg_21": 1124073984,
                        "reg_40": 4079499265,
                        "reg_41": 949450034,
                        "reg_42": 1123749412,
                        "reg_43": 215889455,
                        "reg_44": 193662688,
                        "reg_45": 545378832,
                        "reg_46": 1043251728,
                        "reg_47": 4214024981,
                        "reg_48": 3511875329,
                        "reg_49": 1108364623,
                        "reg_4a": 4043870607,
                        "reg_4b": 3772240052,
                        "reg_4c": 2227376081,
                        "reg_4d": 3969913039,
                        "reg_4e": 1421286680,
                        "reg_4f": 687272932,
                        "reg_50": 2761450545,
                        "reg_51": 4292015183,
                        "reg_52": 3923099502,
                        "reg_53": 4077208091,
                        "reg_54": 3544216412,
                        "reg_55": 3644834812,
                        "reg_56": 1982197698,
                        "reg_57": 3658293547,
                        "reg_58": 600854033,
                        "reg_59": 400290901,
                        "reg_5a": 2688822543,
                        "reg_5b": 958208515,
                        "reg_5c": 4124770591,
                        "reg_5d": 3621864497,
                        "reg_5e": 317911314,
                        "reg_5f": 3774749776,
                        "reg_60": 2395733887,
                        "reg_61": 598210441,
                        "reg_62": 1434253943,
                        "reg_63": 2514164825,
                        "reg_64": 2114983503,
                        "reg_65": 779166846,
                        "reg_66": 3950692315,
                        "reg_67": 1272405838,
                        "reg_68": 4294967295,
                        "reg_69": 4294967295,
                        "reg_6a": 4294967295,
                        "reg_6b": 4294967295,
                        "reg_6c": 4294967295,
                        "reg_6d": 4294967295,
                        "reg_6e": 4294967295,
                        "reg_6f": 4294967295
                    },
                    {
                        "address": 2,
                        "reg_01": 67318220,
                        "reg_02": 25676383,
                        "reg_03": 158531692,
                        "reg_10": 0,
                        "reg_11": 0,
                        "reg_12": 0,
                        "reg_13": 0,
                        "reg_14": 0,
                        "reg_15": 0,
                        "reg_16": 0,
                        "reg_17": 0,
                        "reg_20": 137363512,
                        "reg_21": 1124073984,
                        "reg_40": 4273973628,
                        "reg_41": 501094578,
                        "reg_42": 97460969,
                        "reg_43": 1425080046,
                        "reg_44": 4002060974,
                        "reg_45": 2089620399,
                        "reg_46": 2957831892,
                        "reg_47": 3638018573,
                        "reg_48": 2953264482,
                        "reg_49": 250724910,
                        "reg_4a": 1423814866,
                        "reg_4b": 541318607,
                        "reg_4c": 244258353,
                        "reg_4d": 4023016219,
                        "reg_4e": 4045455707,
                        "reg_4f": 3003304390,
                        "reg_50": 3439914463,
                        "reg_51": 283774668,
                        "reg_52": 3977342478,
                        "reg_53": 3689864290,
                        "reg_54": 1104149562,
                        "reg_55": 2336022605,
                        "reg_56": 453166073,
                        "reg_57": 733611983,
                        "reg_58": 3167879486,
                        "reg_59": 4257344971,
                        "reg_5a": 4195015259,
                        "reg_5b": 3207446029,
                        "reg_5c": 4055215390,
                        "reg_5d": 250729193,
                        "reg_5e": 3672059034,
                        "reg_5f": 2228906764,
                        "reg_60": 3503065344,
                        "reg_61": 375458816,
                        "reg_62": 3771045481,
                        "reg_63": 1886784143,
                        "reg_64": 20629536,
                        "reg_65": 2293507266,
                        "reg_66": 572657686,
                        "reg_67": 34116690,
                        "reg_68": 4294967295,
                        "reg_69": 4294967295,
                        "reg_6a": 4294967295,
                        "reg_6b": 4294967295,
                        "reg_6c": 4294967295,
                        "reg_6d": 4294967295,
                        "reg_6e": 4294967295,
                        "reg_6f": 4294967295
                    },
                    {
                        "address": 3,
                        "reg_01": 67319277,
                        "reg_02": 25676383,
                        "reg_03": 158515308,
                        "reg_10": 0,
                        "reg_11": 0,
                        "reg_12": 0,
                        "reg_13": 0,
                        "reg_14": 0,
                        "reg_15": 0,
                        "reg_16": 0,
                        "reg_17": 0,
                        "reg_20": 137363512,
                        "reg_21": 1124073984,
                        "reg_40": 2008299938,
                        "reg_41": 4221615821,
                        "reg_42": 3494056239,
                        "reg_43": 2470387940,
                        "reg_44": 522499082,
                        "reg_45": 655479324,
                        "reg_46": 1093930752,
                        "reg_47": 1027265738,
                        "reg_48": 187962325,
                        "reg_49": 520872236,
                        "reg_4a": 3217300619,
                        "reg_4b": 3687724421,
                        "reg_4c": 506224431,
                        "reg_4d": 3441214430,
                        "reg_4e": 3599814830,
                        "reg_4f": 737927189,
                        "reg_50": 1245703676,
                        "reg_51": 1677758912,
                        "reg_52": 3269614288,
                        "reg_53": 4014865423,
                        "reg_54": 3735285467,
                        "reg_55": 3961771725,
                        "reg_56": 3240054464,
                        "reg_57": 201600964,
                        "reg_58": 2033373577,
                        "reg_59": 3436567331,
                        "reg_5a": 1643911677,
                        "reg_5b": 823865885,
                        "reg_5c": 4059101794,
                        "reg_5d": 2018237423,
                        "reg_5e": 200616233,
                        "reg_5f": 1061097528,
                        "reg_60": 3984461913,
                        "reg_61": 2767976118,
                        "reg_62": 219850429,
                        "reg_63": 2253661354,
                        "reg_64": 576306592,
                        "reg_65": 3093902352,
                        "reg_66": 4006089654,
                        "reg_67": 2946113619,
                        "reg_68": 4294967295,
                        "reg_69": 4294967295,
                        "reg_6a": 4294967295,
                        "reg_6b": 4294967295,
                        "reg_6c": 4294967295,
                        "reg_6d": 4294967295,
                        "reg_6e": 4294967295,
                        "reg_6f": 4294967295
                    },
                    {
                        "address": 4,
                        "reg_01": 67319277,
                        "reg_02": 25676643,
                        "reg_03": 158548076,
                        "reg_10": 0,
                        "reg_11": 0,
                        "reg_12": 0,
                        "reg_13": 0,
                        "reg_14": 0,
                        "reg_15": 0,
                        "reg_16": 0,
                        "reg_17": 0,
                        "reg_20": 137363512,
                        "reg_21": 1124073984,
                        "reg_40": 746852527,
                        "reg_41": 2370900987,
                        "reg_42": 1356529833,
                        "reg_43": 3753706046,
                        "reg_44": 2164401392,
                        "reg_45": 3490709293,
                        "reg_46": 4056992799,
                        "reg_47": 2684363061,
                        "reg_48": 3254596604,
                        "reg_49": 4076318731,
                        "reg_4a": 252506379,
                        "reg_4b": 753933610,
                        "reg_4c": 3539668240,
                        "reg_4d": 3016297217,
                        "reg_4e": 819633725,
                        "reg_4f": 3179342363,
                        "reg_50": 3085634836,
                        "reg_51": 533720493,
                        "reg_52": 2969579565,
                        "reg_53": 292977999,
                        "reg_54": 1040143363,
                        "reg_55": 4278732830,
                        "reg_56": 4279071896,
                        "reg_57": 1077794463,
                        "reg_58": 558673373,
                        "reg_59": 1863098317,
                        "reg_5a": 3723694577,
                        "reg_5b": 4035244055,
                        "reg_5c": 3823221442,
                        "reg_5d": 1404154587,
                        "reg_5e": 3469652161,
                        "reg_5f": 3910000508,
                        "reg_60": 239877276,
                        "reg_61": 2136105725,
                        "reg_62": 2594592332,
                        "reg_63": 314723147,
                        "reg_64": 3665723467,
                        "reg_65": 3828099719,
                        "reg_66": 1444751584,
                        "reg_67": 570807377,
                        "reg_68": 4294967295,
                        "reg_69": 4294967295,
                        "reg_6a": 4294967295,
                        "reg_6b": 4294967295,
                        "reg_6c": 4294967295,
                        "reg_6d": 4294967295,
                        "reg_6e": 4294967295,
                        "reg_6f": 4294967295
                    },
                    {
                        "address": 5,
                        "reg_01": 67318252,
                        "reg_02": 25676387,
                        "reg_03": 160612460,
                        "reg_10": 0,
                        "reg_11": 0,
                        "reg_12": 0,
                        "reg_13": 0,
                        "reg_14": 0,
                        "reg_15": 0,
                        "reg_16": 0,
                        "reg_17": 0,
                        "reg_20": 137363512,
                        "reg_21": 1124073984,
                        "reg_40": 2647466175,
                        "reg_41": 944361423,
                        "reg_42": 2039425310,
                        "reg_43": 3721251708,
                        "reg_44": 703613678,
                        "reg_45": 3875994607,
                        "reg_46": 2178621641,
                        "reg_47": 3368866685,
                        "reg_48": 2713710554,
                        "reg_49": 3433887148,
                        "reg_4a": 3455785881,
                        "reg_4b": 3398421632,
                        "reg_4c": 2294005056,
                        "reg_4d": 3318597337,
                        "reg_4e": 388652091,
                        "reg_4f": 2952923674,
                        "reg_50": 3557223115,
                        "reg_51": 31202282,
                        "reg_52": 3452104445,
                        "reg_53": 3004301339,
                        "reg_54": 4016966175,
                        "reg_55": 218882039,
                        "reg_56": 3237861917,
                        "reg_57": 1793653693,
                        "reg_58": 167487293,
                        "reg_59": 3705332062,
                        "reg_5a": 2139819732,
                        "reg_5b": 4111068141,
                        "reg_5c": 2212371403,
                        "reg_5d": 3178438400,
                        "reg_5e": 3456829195,
                        "reg_5f": 413764289,
                        "reg_60": 696332,
                        "reg_61": 72097936,
                        "reg_62": 17301568,
                        "reg_63": 2055865345,
                        "reg_64": 2115029088,
                        "reg_65": 4366346,
                        "reg_66": 537396352,
                        "reg_67": 2167020360,
                        "reg_68": 4294967295,
                        "reg_69": 4294967295,
                        "reg_6a": 4294967295,
                        "reg_6b": 4294967295,
                        "reg_6c": 4294967295,
                        "reg_6d": 4294967295,
                        "reg_6e": 4294967295,
                        "reg_6f": 4294967295
                    },
                    {
                        "address": 6,
                        "reg_01": 67318253,
                        "reg_02": 25676379,
                        "reg_03": 160628844,
                        "reg_10": 0,
                        "reg_11": 0,
                        "reg_12": 0,
                        "reg_13": 0,
                        "reg_14": 0,
                        "reg_15": 0,
                        "reg_16": 0,
                        "reg_17": 0,
                        "reg_20": 137363512,
                        "reg_21": 1124073984,
                        "reg_40": 3445440347,
                        "reg_41": 4236492188,
                        "reg_42": 3958287359,
                        "reg_43": 4057863948,
                        "reg_44": 3985611691,
                        "reg_45": 4020831230,
                        "reg_46": 3274505284,
                        "reg_47": 3436174844,
                        "reg_48": 3267698338,
                        "reg_49": 1768755440,
                        "reg_4a": 3964353215,
                        "reg_4b": 3537915060,
                        "reg_4c": 4291550899,
                        "reg_4d": 3469856766,
                        "reg_4e": 3552751802,
                        "reg_4f": 2124562494,
                        "reg_50": 3270173916,
                        "reg_51": 4043105803,
                        "reg_52": 2718081220,
                        "reg_53": 31643531,
                        "reg_54": 3751206422,
                        "reg_55": 4012116671,
                        "reg_56": 3788513936,
                        "reg_57": 1041108428,
                        "reg_58": 989540801,
                        "reg_59": 53105655,
                        "reg_5a": 479902848,
                        "reg_5b": 310246874,
                        "reg_5c": 320461114,
                        "reg_5d": 4291314204,
                        "reg_5e": 3167728628,
                        "reg_5f": 3142218263,
                        "reg_60": 1241518632,
                        "reg_61": 6491168,
                        "reg_62": 1495838041,
                        "reg_63": 508825601,
                        "reg_64": 3496297028,
                        "reg_65": 2824681474,
                        "reg_66": 3229740173,
                        "reg_67": 100994786,
                        "reg_68": 4294967295,
                        "reg_69": 4294967295,
                        "reg_6a": 4294967295,
                        "reg_6b": 4294967295,
                        "reg_6c": 4294967295,
                        "reg_6d": 4294967295,
                        "reg_6e": 4294967295,
                        "reg_6f": 4294967295
                    },
                    {
                        "address": 7,
                        "reg_01": 67318220,
                        "reg_02": 25676627,
                        "reg_03": 160628844,
                        "reg_10": 0,
                        "reg_11": 0,
                        "reg_12": 0,
                        "reg_13": 0,
                        "reg_14": 0,
                        "reg_15": 0,
                        "reg_16": 0,
                        "reg_17": 0,
                        "reg_20": 137363512,
                        "reg_21": 1124073984,
                        "reg_40": 3200376493,
                        "reg_41": 4106501359,
                        "reg_42": 18692768,
                        "reg_43": 3986778544,
                        "reg_44": 3612403732,
                        "reg_45": 3415207552,
                        "reg_46": 1610603834,
                        "reg_47": 3538889689,
                        "reg_48": 351267159,
                        "reg_49": 2903234991,
                        "reg_4a": 3789386365,
                        "reg_4b": 967548475,
                        "reg_4c": 2652891871,
                        "reg_4d": 3723100664,
                        "reg_4e": 281485714,
                        "reg_4f": 2564734689,
                        "reg_50": 804253380,
                        "reg_51": 4273740944,
                        "reg_52": 3503080120,
                        "reg_53": 2632445727,
                        "reg_54": 3158367422,
                        "reg_55": 503509206,
                        "reg_56": 3520372907,
                        "reg_57": 3902717183,
                        "reg_58": 4174155982,
                        "reg_59": 3251219744,
                        "reg_5a": 2650053277,
                        "reg_5b": 816351887,
                        "reg_5c": 252612761,
                        "reg_5d": 1305452639,
                        "reg_5e": 1704718092,
                        "reg_5f": 482130490,
                        "reg_60": 434722832,
                        "reg_61": 1216479539,
                        "reg_62": 2185502914,
                        "reg_63": 30215168,
                        "reg_64": 38013313,
                        "reg_65": 5551120,
                        "reg_66": 3221242628,
                        "reg_67": 2181203620,
                        "reg_68": 4294967295,
                        "reg_69": 4294967295,
                        "reg_6a": 4294967295,
                        "reg_6b": 4294967295,
                        "reg_6c": 4294967295,
                        "reg_6d": 4294967295,
                        "reg_6e": 4294967295,
                        "reg_6f": 4294967295
                    },
                    {
                        "address": 8,
                        "reg_01": 67318220,
                        "reg_02": 25676623,
                        "reg_03": 158531692,
                        "reg_10": 0,
                        "reg_11": 0,
                        "reg_12": 0,
                        "reg_13": 0,
                        "reg_14": 0,
                        "reg_15": 0,
                        "reg_16": 0,
                        "reg_17": 0,
                        "reg_20": 137363512,
                        "reg_21": 1124073984,
                        "reg_40": 2866246851,
                        "reg_41": 4207882205,
                        "reg_42": 3402360507,
                        "reg_43": 3115130607,
                        "reg_44": 3455246002,
                        "reg_45": 2667302201,
                        "reg_46": 2627477785,
                        "reg_47": 1025546221,
                        "reg_48": 3986647967,
                        "reg_49": 4006476486,
                        "reg_4a": 3903187740,
                        "reg_4b": 986574237,
                        "reg_4c": 1267828939,
                        "reg_4d": 3916220355,
                        "reg_4e": 3922520089,
                        "reg_4f": 2314901461,
                        "reg_50": 4273418176,
                        "reg_51": 4025472954,
                        "reg_52": 4098707121,
                        "reg_53": 3754149341,
                        "reg_54": 4017193212,
                        "reg_55": 3701152237,
                        "reg_56": 739973823,
                        "reg_57": 771677134,
                        "reg_58": 3772635799,
                        "reg_59": 222026440,
                        "reg_5a": 24173304,
                        "reg_5b": 1927408557,
                        "reg_5c": 3441029155,
                        "reg_5d": 3273436219,
                        "reg_5e": 2968194351,
                        "reg_5f": 3654859431,
                        "reg_60": 134219781,
                        "reg_61": 2685272593,
                        "reg_62": 2147614720,
                        "reg_63": 131472,
                        "reg_64": 273220617,
                        "reg_65": 2158495764,
                        "reg_66": 1355849792,
                        "reg_67": 4874791,
                        "reg_68": 4294967295,
                        "reg_69": 4294967295,
                        "reg_6a": 4294967295,
                        "reg_6b": 4294967295,
                        "reg_6c": 4294967295,
                        "reg_6d": 4294967295,
                        "reg_6e": 4294967295,
                        "reg_6f": 4294967295
                    },
                    {
                        "address": 9,
                        "reg_01": 67318220,
                        "reg_02": 25676631,
                        "reg_03": 160628844,
                        "reg_10": 0,
                        "reg_11": 0,
                        "reg_12": 0,
                        "reg_13": 0,
                        "reg_14": 0,
                        "reg_15": 0,
                        "reg_16": 0,
                        "reg_17": 0,
                        "reg_20": 137363512,
                        "reg_21": 1124073984,
                        "reg_40": 466791153,
                        "reg_41": 3205362938,
                        "reg_42": 228095443,
                        "reg_43": 2968249609,
                        "reg_44": 834703895,
                        "reg_45": 2628369805,
                        "reg_46": 3490699516,
                        "reg_47": 4253794366,
                        "reg_48": 2666717152,
                        "reg_49": 2798503879,
                        "reg_4a": 3723428796,
                        "reg_4b": 2143936516,
                        "reg_4c": 2728251391,
                        "reg_4d": 2982591962,
                        "reg_4e": 3114126859,
                        "reg_4f": 3581001837,
                        "reg_50": 3572246990,
                        "reg_51": 2969099056,
                        "reg_52": 1363149788,
                        "reg_53": 2653286224,
                        "reg_54": 1275258622,
                        "reg_55": 4057736382,
                        "reg_56": 3922727072,
                        "reg_57": 4040966352,
                        "reg_58": 3494570943,
                        "reg_59": 2305670055,
                        "reg_5a": 157396270,
                        "reg_5b": 804118160,
                        "reg_5c": 1051923144,
                        "reg_5d": 3470414013,
                        "reg_5e": 2665402344,
                        "reg_5f": 3186683290,
                        "reg_60": 1182868625,
                        "reg_61": 106954966,
                        "reg_62": 118226961,
                        "reg_63": 369246272,
                        "reg_64": 603734792,
                        "reg_65": 1293765812,
                        "reg_66": 2173829216,
                        "reg_67": 268438684,
                        "reg_68": 4294967295,
                        "reg_69": 4294967295,
                        "reg_6a": 4294967295,
                        "reg_6b": 4294967295,
                        "reg_6c": 4294967295,
                        "reg_6d": 4294967295,
                        "reg_6e": 4294967295,
                        "reg_6f": 4294967295
                    }
                ],
                "chipset": "ABCStarv1 + HCCStarv1",
                "hcc": {
                    "address": 2,
                    "regs": [
                        42991616,
                        2863311530,
                        2730,
                        16726789,
                        0,
                        0,
                        214748364,
                        20,
                        2046,
                        196624,
                        196624,
                        139,
                        15,
                        1,
                        1,
                        0,
                        4285952
                    ]
                },
                "pos_to_addr": [
                    0,
                    1,
                    2,
                    3,
                    4,
                    5,
                    6,
                    7,
                    8,
                    9
                ],
                "pos_to_id": [
                    0,
                    1,
                    2,
                    3,
                    4,
                    5,
                    6,
                    7,
                    8,
                    9
                ],
                "stream": "2"
            },
            {
                "ccr": "0",
                "chips": [
                    {
                        "address": 0,
                        "reg_01": 67318220,
                        "reg_02": 25676383,
                        "reg_03": 158515308,
                        "reg_10": 0,
                        "reg_11": 0,
                        "reg_12": 0,
                        "reg_13": 0,
                        "reg_14": 0,
                        "reg_15": 0,
                        "reg_16": 0,
                        "reg_17": 0,
                        "reg_20": 137363512,
                        "reg_21": 1124073984,
                        "reg_40": 4026420946,
                        "reg_41": 1040201004,
                        "reg_42": 3222692113,
                        "reg_43": 4008909739,
                        "reg_44": 1328283840,
                        "reg_45": 219163405,
                        "reg_46": 98297271,
                        "reg_47": 3188592141,
                        "reg_48": 840913074,
                        "reg_49": 601899246,
                        "reg_4a": 254149371,
                        "reg_4b": 4250055648,
                        "reg_4c": 203623822,
                        "reg_4d": 835777505,
                        "reg_4e": 698997920,
                        "reg_4f": 1106620527,
                        "reg_50": 2732396465,
                        "reg_51": 3803712825,
                        "reg_52": 3976228618,
                        "reg_53": 353157390,
                        "reg_54": 1807530949,
                        "reg_55": 3506237934,
                        "reg_56": 563811311,
                        "reg_57": 705335870,
                        "reg_58": 3771666975,
                        "reg_59": 3792719385,
                        "reg_5a": 15706673,
                        "reg_5b": 1419968013,
                        "reg_5c": 4086055799,
                        "reg_5d": 4092469299,
                        "reg_5e": 508559001,
                        "reg_5f": 3924957616,
                        "reg_60": 411024905,
                        "reg_61": 717535917,
                        "reg_62": 901569773,
                        "reg_63": 3330364856,
                        "reg_64": 3862584137,
                        "reg_65": 2934719617,
                        "reg_66": 3536026190,
                        "reg_67": 497045359,
                        "reg_68": 4294967295,
                        "reg_69": 4294967295,
                        "reg_6a": 4294967295,
                        "reg_6b": 4294967295,
                        "reg_6c": 4294967295,
                        "reg_6d": 4294967295,
                        "reg_6e": 4294967295,
                        "reg_6f": 4294967295
                    },
                    {
                        "address": 1,
                        "reg_01": 67319277,
                        "reg_02": 25676371,
                        "reg_03": 156418156,
                        "reg_10": 0,
                        "reg_11": 0,
                        "reg_12": 0,
                        "reg_13": 0,
                        "reg_14": 0,
                        "reg_15": 0,
                        "reg_16": 0,
                        "reg_17": 0,
                        "reg_20": 137363512,
                        "reg_21": 1124073984,
                        "reg_40": 3460709756,
                        "reg_41": 1138962958,
                        "reg_42": 910127592,
                        "reg_43": 2944471108,
                        "reg_44": 1356034881,
                        "reg_45": 1164206996,
                        "reg_46": 232858129,
                        "reg_47": 3855816224,
                        "reg_48": 677388628,
                        "reg_49": 344334865,
                        "reg_4a": 790639910,
                        "reg_4b": 59674854,
                        "reg_4c": 1090577495,
                        "reg_4d": 1982038291,
                        "reg_4e": 265166398,
                        "reg_4f": 4275154723,
                        "reg_50": 262812127,
                        "reg_51": 573072274,
                        "reg_52": 22019448,
                        "reg_53": 657733425,
                        "reg_54": 4010717982,
                        "reg_55": 2539093567,
                        "reg_56": 1321161701,
                        "reg_57": 2228402244,
                        "reg_58": 3793892222,
                        "reg_59": 454239103,
                        "reg_5a": 3807586069,
                        "reg_5b": 615859270,
                        "reg_5c": 1108865557,
                        "reg_5d": 1169289810,
                        "reg_5e": 2437684032,
                        "reg_5f": 4710127,
                        "reg_60": 3219512895,
                        "reg_61": 1604321247,
                        "reg_62": 3988783103,
                        "reg_63": 462094327,
                        "reg_64": 4293132204,
                        "reg_65": 3616406054,
                        "reg_66": 3747610238,
                        "reg_67": 4041988087,
                        "reg_68": 4294967295,
                        "reg_69": 4294967295,
                        "reg_6a": 4294967295,
                        "reg_6b": 4294967295,
                        "reg_6c": 4294967295,
                        "reg_6d": 4294967295,
                        "reg_6e": 4294967295,
                        "reg_6f": 4294967295
                    },
                    {
                        "address": 2,
                        "reg_01": 67317196,
                        "reg_02": 25676371,
                        "reg_03": 156418156,
                        "reg_10": 0,
                        "reg_11": 0,
                        "reg_12": 0,
                        "reg_13": 0,
                        "reg_14": 0,
                        "reg_15": 0,
                        "reg_16": 0,
                        "reg_17": 0,
                        "reg_20": 137363512,
                        "reg_21": 1124073984,
                        "reg_40": 2276326302,
                        "reg_41": 2876873950,
                        "reg_42": 3116006557,
                        "reg_43": 4259444438,
                        "reg_44": 3678125688,
                        "reg_45": 94371283,
                        "reg_46": 481361689,
                        "reg_47": 3423743499,
                        "reg_48": 1136325264,
                        "reg_49": 215735805,
                        "reg_4a": 3842613416,
                        "reg_4b": 1371409457,
                        "reg_4c": 2189674416,
                        "reg_4d": 3450524315,
                        "reg_4e": 3154824671,
                        "reg_4f": 689532348,
                        "reg_50": 523148958,
                        "reg_51": 2311857355,
                        "reg_52": 3459562188,
                        "reg_53": 4058898171,
                        "reg_54": 4292848829,
                        "reg_55": 81318335,
                        "reg_56": 2926430972,
                        "reg_57": 3980324811,
                        "reg_58": 3459124961,
                        "reg_59": 2628758844,
                        "reg_5a": 1254829037,
                        "reg_5b": 2929503483,
                        "reg_5c": 1459677743,
                        "reg_5d": 3756899743,
                        "reg_5e": 2614009327,
                        "reg_5f": 95211227,
                        "reg_60": 268435456,
                        "reg_61": 982696224,
                        "reg_62": 1260683461,
                        "reg_63": 2686452817,
                        "reg_64": 1076890784,
                        "reg_65": 536921088,
                        "reg_66": 8913449,
                        "reg_67": 3221225522,
                        "reg_68": 4294967295,
                        "reg_69": 4294967295,
                        "reg_6a": 4294967295,
                        "reg_6b": 4294967295,
                        "reg_6c": 4294967295,
                        "reg_6d": 4294967295,
                        "reg_6e": 4294967295,
                        "reg_6f": 4294967295
                    },
                    {
                        "address": 3,
                        "reg_01": 67319277,
                        "reg_02": 25676643,
                        "reg_03": 158515308,
                        "reg_10": 0,
                        "reg_11": 0,
                        "reg_12": 0,
                        "reg_13": 0,
                        "reg_14": 0,
                        "reg_15": 0,
                        "reg_16": 0,
                        "reg_17": 0,
                        "reg_20": 137363512,
                        "reg_21": 1124073984,
                        "reg_40": 553598297,
                        "reg_41": 3004239823,
                        "reg_42": 2608941628,
                        "reg_43": 3465277418,
                        "reg_44": 1355491321,
                        "reg_45": 1244504588,
                        "reg_46": 1472265891,
                        "reg_47": 4014908062,
                        "reg_48": 763601215,
                        "reg_49": 987665310,
                        "reg_4a": 4138855904,
                        "reg_4b": 3975533519,
                        "reg_4c": 3167310152,
                        "reg_4d": 1625492830,
                        "reg_4e": 2493255218,
                        "reg_4f": 3892242366,
                        "reg_50": 4094624242,
                        "reg_51": 1847269315,
                        "reg_52": 4212213954,
                        "reg_53": 4290835430,
                        "reg_54": 1270669602,
                        "reg_55": 3502242887,
                        "reg_56": 1867125217,
                        "reg_57": 4282532803,
                        "reg_58": 455184110,
                        "reg_59": 725670798,
                        "reg_5a": 3277603814,
                        "reg_5b": 3216814546,
                        "reg_5c": 3756988938,
                        "reg_5d": 2701200160,
                        "reg_5e": 3912360509,
                        "reg_5f": 1596842731,
                        "reg_60": 1734858,
                        "reg_61": 613541580,
                        "reg_62": 273745046,
                        "reg_63": 1145821702,
                        "reg_64": 356101485,
                        "reg_65": 1034764935,
                        "reg_66": 91074736,
                        "reg_67": 2755033866,
                        "reg_68": 4294967295,
                        "reg_69": 4294967295,
                        "reg_6a": 4294967295,
                        "reg_6b": 4294967295,
                        "reg_6c": 4294967295,
                        "reg_6d": 4294967295,
                        "reg_6e": 4294967295,
                        "reg_6f": 4294967295
                    },
                    {
                        "address": 4,
                        "reg_01": 67319277,
                        "reg_02": 25676643,
                        "reg_03": 158515308,
                        "reg_10": 0,
                        "reg_11": 0,
                        "reg_12": 0,
                        "reg_13": 0,
                        "reg_14": 0,
                        "reg_15": 0,
                        "reg_16": 0,
                        "reg_17": 0,
                        "reg_20": 137363512,
                        "reg_21": 1124073984,
                        "reg_40": 3448638452,
                        "reg_41": 263262225,
                        "reg_42": 1069088754,
                        "reg_43": 4027366624,
                        "reg_44": 783359181,
                        "reg_45": 4267964111,
                        "reg_46": 45670817,
                        "reg_47": 267057903,
                        "reg_48": 238015896,
                        "reg_49": 3703489262,
                        "reg_4a": 4093692577,
                        "reg_4b": 4026527904,
                        "reg_4c": 620372478,
                        "reg_4d": 4015971774,
                        "reg_4e": 2721176789,
                        "reg_4f": 3487749038,
                        "reg_50": 4061676971,
                        "reg_51": 3727229163,
                        "reg_52": 1847598015,
                        "reg_53": 3723501489,
                        "reg_54": 3154315343,
                        "reg_55": 3789540562,
                        "reg_56": 1125979684,
                        "reg_57": 3963433392,
                        "reg_58": 3508146198,
                        "reg_59": 842469359,
                        "reg_5a": 2026597676,
                        "reg_5b": 3688039979,
                        "reg_5c": 788307098,
                        "reg_5d": 3691135460,
                        "reg_5e": 2732666364,
                        "reg_5f": 183235940,
                        "reg_60": 1635884809,
                        "reg_61": 2160407704,
                        "reg_62": 91292836,
                        "reg_63": 342958284,
                        "reg_64": 423111788,
                        "reg_65": 770392382,
                        "reg_66": 503507055,
                        "reg_67": 2270705024,
                        "reg_68": 4294967295,
                        "reg_69": 4294967295,
                        "reg_6a": 4294967295,
                        "reg_6b": 4294967295,
                        "reg_6c": 4294967295,
                        "reg_6d": 4294967295,
                        "reg_6e": 4294967295,
                        "reg_6f": 4294967295
                    },
                    {
                        "address": 5,
                        "reg_01": 67319277,
                        "reg_02": 25676387,
                        "reg_03": 158531692,
                        "reg_10": 0,
                        "reg_11": 0,
                        "reg_12": 0,
                        "reg_13": 0,
                        "reg_14": 0,
                        "reg_15": 0,
                        "reg_16": 0,
                        "reg_17": 0,
                        "reg_20": 137363512,
                        "reg_21": 1124073984,
                        "reg_40": 3988589746,
                        "reg_41": 2329821214,
                        "reg_42": 2348539499,
                        "reg_43": 3420290814,
                        "reg_44": 3100222494,
                        "reg_45": 277920233,
                        "reg_46": 222227884,
                        "reg_47": 233497450,
                        "reg_48": 3976313552,
                        "reg_49": 9094620,
                        "reg_4a": 1347186928,
                        "reg_4b": 546385114,
                        "reg_4c": 466534157,
                        "reg_4d": 2680088930,
                        "reg_4e": 2814296248,
                        "reg_4f": 2643566284,
                        "reg_50": 812640557,
                        "reg_51": 4023981058,
                        "reg_52": 201268144,
                        "reg_53": 3974870815,
                        "reg_54": 534606099,
                        "reg_55": 3493683265,
                        "reg_56": 1580293778,
                        "reg_57": 3724352795,
                        "reg_58": 531619905,
                        "reg_59": 3972639789,
                        "reg_5a": 3400277743,
                        "reg_5b": 3958377929,
                        "reg_5c": 4038724105,
                        "reg_5d": 3458924268,
                        "reg_5e": 284938962,
                        "reg_5f": 4260306651,
                        "reg_60": 3593,
                        "reg_61": 2258685954,
                        "reg_62": 3638935601,
                        "reg_63": 268697986,
                        "reg_64": 42536898,
                        "reg_65": 179924871,
                        "reg_66": 403177607,
                        "reg_67": 147136586,
                        "reg_68": 4294967295,
                        "reg_69": 4294967295,
                        "reg_6a": 4294967295,
                        "reg_6b": 4294967295,
                        "reg_6c": 4294967295,
                        "reg_6d": 4294967295,
                        "reg_6e": 4294967295,
                        "reg_6f": 4294967295
                    },
                    {
                        "address": 6,
                        "reg_01": 67318220,
                        "reg_02": 25676387,
                        "reg_03": 160596076,
                        "reg_10": 0,
                        "reg_11": 0,
                        "reg_12": 0,
                        "reg_13": 0,
                        "reg_14": 0,
                        "reg_15": 0,
                        "reg_16": 0,
                        "reg_17": 0,
                        "reg_20": 137363512,
                        "reg_21": 1124073984,
                        "reg_40": 1024085452,
                        "reg_41": 3461451213,
                        "reg_42": 3156017264,
                        "reg_43": 842014221,
                        "reg_44": 4224576402,
                        "reg_45": 1674609619,
                        "reg_46": 293946077,
                        "reg_47": 2969627106,
                        "reg_48": 221490439,
                        "reg_49": 3975541547,
                        "reg_4a": 4210232325,
                        "reg_4b": 30122205,
                        "reg_4c": 3167613740,
                        "reg_4d": 3201277444,
                        "reg_4e": 2126245662,
                        "reg_4f": 3200179689,
                        "reg_50": 3257958062,
                        "reg_51": 3945735632,
                        "reg_52": 227745594,
                        "reg_53": 1088537116,
                        "reg_54": 664969201,
                        "reg_55": 2183127730,
                        "reg_56": 3502244608,
                        "reg_57": 3505331967,
                        "reg_58": 3457077231,
                        "reg_59": 3475832814,
                        "reg_5a": 3759980301,
                        "reg_5b": 2887250959,
                        "reg_5c": 417251375,
                        "reg_5d": 847364665,
                        "reg_5e": 2613055518,
                        "reg_5f": 905895649,
                        "reg_60": 4197265576,
                        "reg_61": 1910265089,
                        "reg_62": 3290044082,
                        "reg_63": 131846,
                        "reg_64": 3600428400,
                        "reg_65": 1214244249,
                        "reg_66": 643964960,
                        "reg_67": 3240023684,
                        "reg_68": 4294967295,
                        "reg_69": 4294967295,
                        "reg_6a": 4294967295,
                        "reg_6b": 4294967295,
                        "reg_6c": 4294967295,
                        "reg_6d": 4294967295,
                        "reg_6e": 4294967295,
                        "reg_6f": 4294967295
                    },
                    {
                        "address": 7,
                        "reg_01": 67318252,
                        "reg_02": 25676635,
                        "reg_03": 158531692,
                        "reg_10": 0,
                        "reg_11": 0,
                        "reg_12": 0,
                        "reg_13": 0,
                        "reg_14": 0,
                        "reg_15": 0,
                        "reg_16": 0,
                        "reg_17": 0,
                        "reg_20": 137363512,
                        "reg_21": 1124073984,
                        "reg_40": 280487917,
                        "reg_41": 1093200644,
                        "reg_42": 3593150736,
                        "reg_43": 4044042300,
                        "reg_44": 1023524589,
                        "reg_45": 424754011,
                        "reg_46": 498196528,
                        "reg_47": 1120596318,
                        "reg_48": 472716033,
                        "reg_49": 441387194,
                        "reg_4a": 2215909632,
                        "reg_4b": 3450393072,
                        "reg_4c": 3489262106,
                        "reg_4d": 3136009148,
                        "reg_4e": 2176625849,
                        "reg_4f": 232779505,
                        "reg_50": 3664846020,
                        "reg_51": 3954027981,
                        "reg_52": 957575437,
                        "reg_53": 2579238611,
                        "reg_54": 833441058,
                        "reg_55": 3523325932,
                        "reg_56": 3473870822,
                        "reg_57": 1174143372,
                        "reg_58": 3468670386,
                        "reg_59": 502272269,
                        "reg_5a": 127311984,
                        "reg_5b": 3297749833,
                        "reg_5c": 1016071406,
                        "reg_5d": 3649752474,
                        "reg_5e": 3386890939,
                        "reg_5f": 3232889860,
                        "reg_60": 1852826560,
                        "reg_61": 3331832496,
                        "reg_62": 91990191,
                        "reg_63": 2168456194,
                        "reg_64": 146669625,
                        "reg_65": 2351526091,
                        "reg_66": 1117101569,
                        "reg_67": 1375731868,
                        "reg_68": 4294967295,
                        "reg_69": 4294967295,
                        "reg_6a": 4294967295,
                        "reg_6b": 4294967295,
                        "reg_6c": 4294967295,
                        "reg_6d": 4294967295,
                        "reg_6e": 4294967295,
                        "reg_6f": 4294967295
                    },
                    {
                        "address": 8,
                        "reg_01": 67319277,
                        "reg_02": 25676627,
                        "reg_03": 158531692,
                        "reg_10": 0,
                        "reg_11": 0,
                        "reg_12": 0,
                        "reg_13": 0,
                        "reg_14": 0,
                        "reg_15": 0,
                        "reg_16": 0,
                        "reg_17": 0,
                        "reg_20": 137363512,
                        "reg_21": 1124073984,
                        "reg_40": 438247164,
                        "reg_41": 217126403,
                        "reg_42": 871958934,
                        "reg_43": 836867531,
                        "reg_44": 573377501,
                        "reg_45": 4073588766,
                        "reg_46": 4180916260,
                        "reg_47": 4206561455,
                        "reg_48": 4058981138,
                        "reg_49": 3955396688,
                        "reg_4a": 2470383107,
                        "reg_4b": 3840745934,
                        "reg_4c": 502381789,
                        "reg_4d": 3676088292,
                        "reg_4e": 3746541487,
                        "reg_4f": 4225870575,
                        "reg_50": 3038301470,
                        "reg_51": 724492302,
                        "reg_52": 779862625,
                        "reg_53": 1022881269,
                        "reg_54": 1826618610,
                        "reg_55": 3293433855,
                        "reg_56": 2732780295,
                        "reg_57": 783152444,
                        "reg_58": 232530385,
                        "reg_59": 1083117312,
                        "reg_5a": 551825135,
                        "reg_5b": 239398909,
                        "reg_5c": 114800864,
                        "reg_5d": 3418564098,
                        "reg_5e": 178917741,
                        "reg_5f": 332438798,
                        "reg_60": 3569982440,
                        "reg_61": 137579240,
                        "reg_62": 1282086735,
                        "reg_63": 270541200,
                        "reg_64": 2424678002,
                        "reg_65": 2253545601,
                        "reg_66": 2698562445,
                        "reg_67": 3532529557,
                        "reg_68": 4294967295,
                        "reg_69": 4294967295,
                        "reg_6a": 4294967295,
                        "reg_6b": 4294967295,
                        "reg_6c": 4294967295,
                        "reg_6d": 4294967295,
                        "reg_6e": 4294967295,
                        "reg_6f": 4294967295
                    },
                    {
                        "address": 9,
                        "reg_01": 67318220,
                        "reg_02": 25676631,
                        "reg_03": 160612460,
                        "reg_10": 0,
                        "reg_11": 0,
                        "reg_12": 0,
                        "reg_13": 0,
                        "reg_14": 0,
                        "reg_15": 0,
                        "reg_16": 0,
                        "reg_17": 0,
                        "reg_20": 137363512,
                        "reg_21": 1124073984,
                        "reg_40": 380748500,
                        "reg_41": 551552290,
                        "reg_42": 1608355362,
                        "reg_43": 4263252947,
                        "reg_44": 1874992676,
                        "reg_45": 3041869620,
                        "reg_46": 1292109805,
                        "reg_47": 1068603332,
                        "reg_48": 235631839,
                        "reg_49": 3824110948,
                        "reg_4a": 3774885855,
                        "reg_4b": 1682155286,
                        "reg_4c": 1240199473,
                        "reg_4d": 307048757,
                        "reg_4e": 1603792492,
                        "reg_4f": 1975758820,
                        "reg_50": 298926159,
                        "reg_51": 220399073,
                        "reg_52": 4142664990,
                        "reg_53": 3805810164,
                        "reg_54": 4029551103,
                        "reg_55": 3302863586,
                        "reg_56": 2422350318,
                        "reg_57": 1033205537,
                        "reg_58": 1642251382,
                        "reg_59": 3503407403,
                        "reg_5a": 4095742437,
                        "reg_5b": 1559111789,
                        "reg_5c": 4052419841,
                        "reg_5d": 69010209,
                        "reg_5e": 3485164446,
                        "reg_5f": 3478323520,
                        "reg_60": 764141525,
                        "reg_61": 2646371227,
                        "reg_62": 4151856044,
                        "reg_63": 1370681287,
                        "reg_64": 1498070494,
                        "reg_65": 2675721580,
                        "reg_66": 2323470039,
                        "reg_67": 1024257871,
                        "reg_68": 4294967295,
                        "reg_69": 4294967295,
                        "reg_6a": 4294967295,
                        "reg_6b": 4294967295,
                        "reg_6c": 4294967295,
                        "reg_6d": 4294967295,
                        "reg_6e": 4294967295,
                        "reg_6f": 4294967295
                    }
                ],
                "chipset": "ABCStarv1 + HCCStarv1",
                "hcc": {
                    "address": 3,
                    "regs": [
                        42991616,
                        2863311530,
                        2730,
                        16726789,
                        0,
                        0,
                        214748364,
                        20,
                        2046,
                        196624,
                        196624,
                        139,
                        15,
                        1,
                        1,
                        0,
                        4285952
                    ]
                },
                "pos_to_addr": [
                    0,
                    1,
                    2,
                    3,
                    4,
                    5,
                    6,
                    7,
                    8,
                    9
                ],
                "pos_to_id": [
                    0,
                    1,
                    2,
                    3,
                    4,
                    5,
                    6,
                    7,
                    8,
                    9
                ],
                "stream": "0"
            }
        ]
    },
    "scan_info": {
        "BC ID reset frequency": 0,
        "COM_DELAY": 200,
        "Config frequency": 0,
        "L1A per loop": 1,
        "PULSE_DELAY": 129,
        "Soft reset frequency": 1000,
        "TRIG_DELAY": 20,
        "abc_busy_limit": 5,
        "abort_on_l0id_mismatch": 0,
        "burst max timeouts": 6,
        "burst maxtrigs": 1000000,
        "burst ntrigs": 1024,
        "burst target": 10,
        "burst trtype": 3,
        "burst type": 50,
        "check_l0id_offset": 0,
        "continue_event_count_between_bursts": 0,
        "debug level": 0,
        "do action DCS": 1,
        "do autostop": 1,
        "do calibration loop": 0,
        "do fill evtree": 0,
        "do fits": 1,
        "do mask by cal": 0,
        "do mask test": 0,
        "do pre burst": 0,
        "do threaded burst": 1,
        "do vary ntrigs": 0,
        "do_check_l0id": 0,
        "do_read_post_scan_config": 1,
        "drop_extra_events": 0,
        "dump_raw_data": 0,
        "external_trigger_source": 255,
        "fill_delta_t": 1,
        "fill_timebin_hit_data": 0,
        "fill_tree_counter": 0,
        "hcc_star_select_decoder": 0,
        "one_bank": 0,
        "pack_hitmap_bits": 0,
        "pull_event_by_l0": 1,
        "rate_limit_delay": 0,
        "read_tdc_data": 0,
        "reset_on_l0id_mismatch": 0,
        "save_event_hit_data": 0,
        "save_raw_event_data": 0,
        "save_trigger_data": 0,
        "send signals": 0,
        "send_raw_event_data": 0,
        "send_signal_event_offset": 0,
        "signal_filler_events": 0,
        "throw away triggers": 0,
        "trigger_single_packet": 1,
        "ttc_busy_limit": 5,
        "wait_external_trigger_timeout": 5
    },
    "scan_points": {
        "scan_type": 1,
        "scan_type_string": "THRESHOLD (DAC)",
        "scan_values": [
            0.0,
            1.0,
            2.0,
            3.0,
            4.0,
            5.0,
            6.0,
            7.0,
            8.0,
            9.0,
            10.0,
            11.0,
            12.0,
            13.0,
            14.0,
            15.0,
            16.0,
            17.0,
            18.0,
            19.0,
            20.0,
            21.0,
            22.0,
            23.0,
            24.0,
            25.0,
            26.0,
            27.0,
            28.0,
            29.0,
            30.0,
            31.0,
            32.0,
            33.0,
            34.0,
            35.0,
            36.0,
            37.0,
            38.0,
            39.0,
            40.0,
            41.0,
            42.0,
            43.0,
            44.0,
            45.0,
            46.0,
            47.0,
            48.0,
            49.0,
            50.0,
            51.0,
            52.0,
            53.0,
            54.0,
            55.0,
            56.0,
            57.0,
            58.0,
            59.0,
            60.0,
            61.0,
            62.0,
            63.0,
            64.0,
            65.0,
            66.0,
            67.0,
            68.0,
            69.0,
            70.0,
            71.0,
            72.0,
            73.0,
            74.0,
            75.0,
            76.0,
            77.0,
            78.0,
            79.0,
            80.0,
            81.0,
            82.0,
            83.0,
            84.0,
            85.0,
            86.0,
            87.0,
            88.0,
            89.0,
            90.0,
            91.0,
            92.0,
            93.0,
            94.0,
            95.0,
            96.0,
            97.0,
            98.0,
            99.0,
            100.0,
            101.0,
            102.0,
            103.0,
            104.0,
            105.0,
            106.0,
            107.0,
            108.0,
            109.0,
            110.0,
            111.0,
            112.0,
            113.0
        ]
    },
    "schema_version": 2,
    "system_info": {
        "GIT Describe": "itsdaq_23_3_2023-1010-gb4aa7d11a",
        "GIT URL": "https://gitlab.cern.ch/atlas-itk-strips-daq/itsdaq-sw.git/-/tree/b4aa7d11a918d9ff057ec56f477d9ccee74cce97",
        "GIT branch": "",
        "GIT commit date": "2023-11-24 23:54:30 +0000 (Fri, 24 Nov 2023)",
        "GIT info extracted": "2023-11-28 09:52:01 +0000 (Tue, 28 Nov 2023)",
        "GIT modified": "locally modified",
        "GIT revision": "b4aa7d11a918d9ff057ec56f477d9ccee74cce97",
        "dedication": "New dedication as we're going for PPA",
        "firmware": "0xb66d"
    },
    "trigger_sequence": [
        {
            "command": "cal_pulse"
        },
        {
            "delay": 20
        },
        {
            "command": "none"
        },
        {
            "delay": 0
        },
        {
            "loop": {
                "count": 1,
                "sequence": [
                    {
                        "command": "trigger"
                    },
                    {
                        "delay": 0
                    }
                ]
            }
        }
    ]
}
